bible_verse/__init__.py
bible_verse/main.py
bible_verse-0.2.0.dist-info/entry_points.txt
bible_verse-0.2.0.dist-info/METADATA
bible_verse-0.2.0.dist-info/WHEEL
bible_verse-0.2.0.dist-info/RECORD
