Metadata-Version: 2.1
Name: bible_verse
Version: 0.2.0
Summary: 
Author: AnaJuliaMM
Author-email: ana.martins_2004@outlook.com
Requires-Python: >=3.11,<4.0
Classifier: Programming Language :: Python :: 3
Classifier: Programming Language :: Python :: 3.11
Classifier: Programming Language :: Python :: 3.12
